setup.py
bin/lov2pi
lov2pi/__init__.py
lov2pi/connections.py
lov2pi/detect.py
lov2pi/device.py
lov2pi/handlers.py
lov2pi/main.py
lov2pi.egg-info/PKG-INFO
lov2pi.egg-info/SOURCES.txt
lov2pi.egg-info/dependency_links.txt
lov2pi.egg-info/not-zip-safe
lov2pi.egg-info/pbr.json
lov2pi.egg-info/requires.txt
lov2pi.egg-info/top_level.txt