Metadata-Version: 1.0
Name: lov2pi
Version: 0.2.0
Summary: Python sdk for lov2pi webservice
Home-page: https://github.com/nyo16/lov2pi
Author: Nikos Maroulis
Author-email: nik.maroulis@gmail.com
License: MIT
Platform: UNKNOWN
